cothread-2.20.1.dist-info/WHEEL
cothread-2.20.1.dist-info/entry_points.txt
cothread-2.20.1.dist-info/METADATA
cothread-2.20.1.dist-info/RECORD
cothread-2.20.1.dist-info/top_level.txt
cothread-2.20.1.dist-info/licenses/COPYING
cothread-2.20.1.dist-info/licenses/LICENSE
cothread/coselect.py
cothread/__init__.py
cothread/_coroutine.cpython-312-x86_64-linux-gnu.so
cothread/input_hook.py
cothread/_version.py
cothread/coserver.py
cothread/cosocket.py
cothread/dbr.py
cothread/poll_win32.py
cothread/cothread.py
cothread/pv.py
cothread/qt.py
cothread/load_ca.py
cothread/cadef.py
cothread/catools.py
cothread/tools/__init__.py
cothread/tools/pvtree.py
